.gitignore
MANIFEST.in
README.rst
bootstrap.py
buildout.cfg
setup.py
collective/__init__.py
collective.js.simplecart.egg-info/PKG-INFO
collective.js.simplecart.egg-info/SOURCES.txt
collective.js.simplecart.egg-info/dependency_links.txt
collective.js.simplecart.egg-info/entry_points.txt
collective.js.simplecart.egg-info/namespace_packages.txt
collective.js.simplecart.egg-info/not-zip-safe
collective.js.simplecart.egg-info/requires.txt
collective.js.simplecart.egg-info/top_level.txt
collective/js/__init__.py
collective/js/simplecart/__init__.py
collective/js/simplecart/configure.zcml
collective/js/simplecart/upgrades.py
collective/js/simplecart/upgrades.zcml
collective/js/simplecart/profiles/default/jsregistry.xml
collective/js/simplecart/profiles/default/metadata.xml
collective/js/simplecart/resources/README.md
collective/js/simplecart/resources/simpleCart.js
collective/js/simplecart/resources/simpleCart.min.js
docs/HISTORY.txt