Metadata-Version: 1.0
Name: collective.js.simplecart
Version: 1.0
Summary: SimpleCart(js) for Plone
Home-page: https://github.com/collective/collective.js.simplecart
Author: JeanMichel FRANCOIS
Author-email: toutpt@gmail.com
License: GPL
Keywords: plone cart javascripts
Platform: UNKNOWN
Classifier: Environment :: Web Environment
Classifier: License :: OSI Approved :: GNU General Public License (GPL)
Classifier: Operating System :: OS Independent
Classifier: Framework :: Plone
Classifier: Framework :: Plone :: 4.0
Classifier: Framework :: Plone :: 4.1
Classifier: Framework :: Plone :: 4.2
Classifier: Programming Language :: Python
